arcade_zoho_books_api/__init__.py
arcade_zoho_books_api/tools/__init__.py
arcade_zoho_books_api/tools/request_body_schemas.py
arcade_zoho_books_api/wrapper_tools/AcceptEstimate.json
arcade_zoho_books_api/wrapper_tools/ActivateBankAccount.json
arcade_zoho_books_api/wrapper_tools/ActivateChartOfAccount.json
arcade_zoho_books_api/wrapper_tools/ActivateContact.json
arcade_zoho_books_api/wrapper_tools/ActivateFixedAsset.json
arcade_zoho_books_api/wrapper_tools/ActivateInactiveItem.json
arcade_zoho_books_api/wrapper_tools/ActivateInactiveUser.json
arcade_zoho_books_api/wrapper_tools/ActivateInvoiceReminder.json
arcade_zoho_books_api/wrapper_tools/ActivateLocation.json
arcade_zoho_books_api/wrapper_tools/ActivateProject.json
arcade_zoho_books_api/wrapper_tools/AddCommentToBill.json
arcade_zoho_books_api/wrapper_tools/AddContactAddress.json
arcade_zoho_books_api/wrapper_tools/AddCreditNoteComment.json
arcade_zoho_books_api/wrapper_tools/AddEstimateComment.json
arcade_zoho_books_api/wrapper_tools/AddFixedAssetComment.json
arcade_zoho_books_api/wrapper_tools/AddInvoiceComment.json
arcade_zoho_books_api/wrapper_tools/AddJournalComment.json
arcade_zoho_books_api/wrapper_tools/AddProjectTask.json
arcade_zoho_books_api/wrapper_tools/AddPurchaseOrderComment.json
arcade_zoho_books_api/wrapper_tools/AddRetainerInvoiceComment.json
arcade_zoho_books_api/wrapper_tools/AddSalesOrderComment.json
arcade_zoho_books_api/wrapper_tools/AddVendorCreditComment.json
arcade_zoho_books_api/wrapper_tools/ApplyCreditNoteToInvoice.json
arcade_zoho_books_api/wrapper_tools/ApplyCreditsToInvoice.json
arcade_zoho_books_api/wrapper_tools/ApplyVendorCreditToBill.json
arcade_zoho_books_api/wrapper_tools/ApplyVendorCreditsToBill.json
arcade_zoho_books_api/wrapper_tools/ApproveBill.json
arcade_zoho_books_api/wrapper_tools/ApproveCreditNote.json
arcade_zoho_books_api/wrapper_tools/ApproveEstimate.json
arcade_zoho_books_api/wrapper_tools/ApproveInvoice.json
arcade_zoho_books_api-1.0.0.dist-info/METADATA
arcade_zoho_books_api-1.0.0.dist-info/WHEEL
arcade_zoho_books_api-1.0.0.dist-info/entry_points.txt
arcade_zoho_books_api-1.0.0.dist-info/licenses/LICENSE
arcade_zoho_books_api-1.0.0.dist-info/RECORD
